bricks_for_python/__init__.py
bricks_for_python/init.py
bricks_for_python-0.0.5.dist-info/METADATA
bricks_for_python-0.0.5.dist-info/WHEEL
bricks_for_python-0.0.5.dist-info/top_level.txt
bricks_for_python-0.0.5.dist-info/RECORD
