Metadata-Version: 2.4
Name: bricks_for_python
Version: 0.0.5
Summary: A packing module for bricks
Author: "yu moqing"
Author-email: "yumoqing@gmail.com"
License: "MIT"
